argparse_director.py
argparse_director-0.4.1.dist-info/LICENSE
argparse_director-0.4.1.dist-info/METADATA
argparse_director-0.4.1.dist-info/WHEEL
argparse_director-0.4.1.dist-info/top_level.txt
argparse_director-0.4.1.dist-info/RECORD
