Metadata-Version: 2.1
Name: argparse-director
Version: 0.4.1
Summary: Simpler, more powerful drop-in replacement for argparser adding configuration files containing executable code, hidden and grouped arguments
Home-page: https://github.com/sneiman/argparse_director
Author: Seth Neiman
Author-email: seth@duckpapa.com
License: UNKNOWN
Platform: UNKNOWN
Classifier: Programming Language :: Python :: 3
Classifier: License :: OSI Approved :: MIT License
Classifier: Operating System :: OS Independent
Requires-Python: >=3.6
